blossomv/__init__.py
blossomv/blossomv.cpython-37m-darwin.so
blossomv-2.4.dist-info/LICENSE
blossomv-2.4.dist-info/METADATA
blossomv-2.4.dist-info/WHEEL
blossomv-2.4.dist-info/top_level.txt
blossomv-2.4.dist-info/RECORD
