Metadata-Version: 2.1
Name: blossomv
Version: 2.4
Summary: A wrapper for the BlossomV code
Home-page: https://github.com/amcpherson/blossomv
Author: Andrew McPherson
Author-email: andrew.mcpherson@gmail.com
License: UNKNOWN
Platform: UNKNOWN
Classifier: Programming Language :: Python :: 3
